UsmanMath/__init__.py
UsmanMath/math.py
uMath-1.0.0.dist-info/LICENSE
uMath-1.0.0.dist-info/METADATA
uMath-1.0.0.dist-info/WHEEL
uMath-1.0.0.dist-info/top_level.txt
uMath-1.0.0.dist-info/RECORD
