Metadata-Version: 2.1
Name: uMath
Version: 1.0.0
Summary: It provides some useful math functions
Home-page: https://github.com/UsmanMaan324/uMath
Author: Usman Ali
Author-email: usmanalianjum04@gmail.com
License: MIT
Platform: UNKNOWN
Classifier: License :: OSI Approved :: MIT License
Classifier: Programming Language :: Python :: 3.6
Classifier: Programming Language :: Python :: 3.7
Classifier: Programming Language :: Python :: 3.8
License-File: LICENSE
